{
  "project_info": {
    "project_number": "687367600472",
    "firebase_url": "https://switch-fb9d8-default-rtdb.asia-southeast1.firebasedatabase.app",
    "project_id": "switch-fb9d8",
    "storage_bucket": "switch-fb9d8.firebasestorage.app"
  },
  "client": [
    {
      "client_info": {
        "mobilesdk_app_id": "1:687367600472:android:1c00f5ffcc6e7bc6d0cd2d",
        "android_client_info": {
          "package_name": "com.sumanshri.smartswitch"
        }
      },
      "oauth_client": [],
      "api_key": [
        {
          "current_key": "AIzaSyB29osrliYp19s4Mw7eoP-jea5C07Qpwcw"
        }
      ],
      "services": {
        "appinvite_service": {
          "other_platform_oauth_client": []
        }
      }
    }
  ],
  "configuration_version": "1"
}